{
  "id": "79d22f64-c54d-4e75-ba33-b5491befd856",
  "prevId": "00000000-0000-0000-0000-000000000000",
  "version": "7",
  "dialect": "postgresql",
  "tables": {
    "public.audit_logs": {
      "name": "audit_logs",
      "schema": "",
      "columns": {
        "id": {
          "name": "id",
          "type": "text",
          "primaryKey": true,
          "notNull": true
        },
        "entity": {
          "name": "entity",
          "type": "text",
          "primaryKey": false,
          "notNull": true
        },
        "entity_id": {
          "name": "entity_id",
          "type": "text",
          "primaryKey": false,
          "notNull": false
        },
        "action": {
          "name": "action",
          "type": "text",
          "primaryKey": false,
          "notNull": true
        },
        "actor_id": {
          "name": "actor_id",
          "type": "text",
          "primaryKey": false,
          "notNull": false
        },
        "actor_role": {
          "name": "actor_role",
          "type": "text",
          "primaryKey": false,
          "notNull": false
        },
        "metadata": {
          "name": "metadata",
          "type": "json",
          "primaryKey": false,
          "notNull": false
        },
        "ip_address": {
          "name": "ip_address",
          "type": "text",
          "primaryKey": false,
          "notNull": false
        },
        "created_at": {
          "name": "created_at",
          "type": "timestamp with time zone",
          "primaryKey": false,
          "notNull": true,
          "default": "now()"
        }
      },
      "indexes": {},
      "foreignKeys": {},
      "compositePrimaryKeys": {},
      "uniqueConstraints": {},
      "policies": {},
      "checkConstraints": {},
      "isRLSEnabled": false
    },
    "public.cities": {
      "name": "cities",
      "schema": "",
      "columns": {
        "id": {
          "name": "id",
          "type": "text",
          "primaryKey": true,
          "notNull": true
        },
        "name": {
          "name": "name",
          "type": "text",
          "primaryKey": false,
          "notNull": true
        },
        "country": {
          "name": "country",
          "type": "text",
          "primaryKey": false,
          "notNull": true
        },
        "state": {
          "name": "state",
          "type": "text",
          "primaryKey": false,
          "notNull": false
        },
        "timezone": {
          "name": "timezone",
          "type": "text",
          "primaryKey": false,
          "notNull": true,
          "default": "'UTC'"
        },
        "is_active": {
          "name": "is_active",
          "type": "boolean",
          "primaryKey": false,
          "notNull": true,
          "default": true
        },
        "lat": {
          "name": "lat",
          "type": "double precision",
          "primaryKey": false,
          "notNull": false
        },
        "lng": {
          "name": "lng",
          "type": "double precision",
          "primaryKey": false,
          "notNull": false
        },
        "created_at": {
          "name": "created_at",
          "type": "timestamp with time zone",
          "primaryKey": false,
          "notNull": true,
          "default": "now()"
        },
        "updated_at": {
          "name": "updated_at",
          "type": "timestamp with time zone",
          "primaryKey": false,
          "notNull": true,
          "default": "now()"
        }
      },
      "indexes": {},
      "foreignKeys": {},
      "compositePrimaryKeys": {},
      "uniqueConstraints": {},
      "policies": {},
      "checkConstraints": {},
      "isRLSEnabled": false
    },
    "public.customer_profiles": {
      "name": "customer_profiles",
      "schema": "",
      "columns": {
        "id": {
          "name": "id",
          "type": "text",
          "primaryKey": true,
          "notNull": true
        },
        "user_id": {
          "name": "user_id",
          "type": "text",
          "primaryKey": false,
          "notNull": true
        },
        "preferred_payment_method": {
          "name": "preferred_payment_method",
          "type": "text",
          "primaryKey": false,
          "notNull": false
        },
        "total_trips": {
          "name": "total_trips",
          "type": "integer",
          "primaryKey": false,
          "notNull": true,
          "default": 0
        },
        "created_at": {
          "name": "created_at",
          "type": "timestamp with time zone",
          "primaryKey": false,
          "notNull": true,
          "default": "now()"
        },
        "updated_at": {
          "name": "updated_at",
          "type": "timestamp with time zone",
          "primaryKey": false,
          "notNull": true,
          "default": "now()"
        }
      },
      "indexes": {},
      "foreignKeys": {
        "customer_profiles_user_id_users_id_fk": {
          "name": "customer_profiles_user_id_users_id_fk",
          "tableFrom": "customer_profiles",
          "tableTo": "users",
          "columnsFrom": [
            "user_id"
          ],
          "columnsTo": [
            "id"
          ],
          "onDelete": "cascade",
          "onUpdate": "no action"
        }
      },
      "compositePrimaryKeys": {},
      "uniqueConstraints": {
        "customer_profiles_user_id_unique": {
          "name": "customer_profiles_user_id_unique",
          "nullsNotDistinct": false,
          "columns": [
            "user_id"
          ]
        }
      },
      "policies": {},
      "checkConstraints": {},
      "isRLSEnabled": false
    },
    "public.driver_profiles": {
      "name": "driver_profiles",
      "schema": "",
      "columns": {
        "id": {
          "name": "id",
          "type": "text",
          "primaryKey": true,
          "notNull": true
        },
        "user_id": {
          "name": "user_id",
          "type": "text",
          "primaryKey": false,
          "notNull": true
        },
        "license_number": {
          "name": "license_number",
          "type": "text",
          "primaryKey": false,
          "notNull": false
        },
        "vehicle_make": {
          "name": "vehicle_make",
          "type": "text",
          "primaryKey": false,
          "notNull": false
        },
        "vehicle_model": {
          "name": "vehicle_model",
          "type": "text",
          "primaryKey": false,
          "notNull": false
        },
        "vehicle_year": {
          "name": "vehicle_year",
          "type": "integer",
          "primaryKey": false,
          "notNull": false
        },
        "vehicle_color": {
          "name": "vehicle_color",
          "type": "text",
          "primaryKey": false,
          "notNull": false
        },
        "vehicle_plate": {
          "name": "vehicle_plate",
          "type": "text",
          "primaryKey": false,
          "notNull": false
        },
        "status": {
          "name": "status",
          "type": "driver_status",
          "typeSchema": "public",
          "primaryKey": false,
          "notNull": true,
          "default": "'OFFLINE'"
        },
        "is_verified": {
          "name": "is_verified",
          "type": "boolean",
          "primaryKey": false,
          "notNull": true,
          "default": false
        },
        "current_lat": {
          "name": "current_lat",
          "type": "double precision",
          "primaryKey": false,
          "notNull": false
        },
        "current_lng": {
          "name": "current_lng",
          "type": "double precision",
          "primaryKey": false,
          "notNull": false
        },
        "last_seen": {
          "name": "last_seen",
          "type": "timestamp with time zone",
          "primaryKey": false,
          "notNull": false
        },
        "city_id": {
          "name": "city_id",
          "type": "text",
          "primaryKey": false,
          "notNull": false
        },
        "rating": {
          "name": "rating",
          "type": "numeric(3, 2)",
          "primaryKey": false,
          "notNull": false
        },
        "total_trips": {
          "name": "total_trips",
          "type": "integer",
          "primaryKey": false,
          "notNull": true,
          "default": 0
        },
        "created_at": {
          "name": "created_at",
          "type": "timestamp with time zone",
          "primaryKey": false,
          "notNull": true,
          "default": "now()"
        },
        "updated_at": {
          "name": "updated_at",
          "type": "timestamp with time zone",
          "primaryKey": false,
          "notNull": true,
          "default": "now()"
        }
      },
      "indexes": {},
      "foreignKeys": {
        "driver_profiles_user_id_users_id_fk": {
          "name": "driver_profiles_user_id_users_id_fk",
          "tableFrom": "driver_profiles",
          "tableTo": "users",
          "columnsFrom": [
            "user_id"
          ],
          "columnsTo": [
            "id"
          ],
          "onDelete": "cascade",
          "onUpdate": "no action"
        },
        "driver_profiles_city_id_cities_id_fk": {
          "name": "driver_profiles_city_id_cities_id_fk",
          "tableFrom": "driver_profiles",
          "tableTo": "cities",
          "columnsFrom": [
            "city_id"
          ],
          "columnsTo": [
            "id"
          ],
          "onDelete": "no action",
          "onUpdate": "no action"
        }
      },
      "compositePrimaryKeys": {},
      "uniqueConstraints": {
        "driver_profiles_user_id_unique": {
          "name": "driver_profiles_user_id_unique",
          "nullsNotDistinct": false,
          "columns": [
            "user_id"
          ]
        }
      },
      "policies": {},
      "checkConstraints": {},
      "isRLSEnabled": false
    },
    "public.driver_zone_assignments": {
      "name": "driver_zone_assignments",
      "schema": "",
      "columns": {
        "id": {
          "name": "id",
          "type": "text",
          "primaryKey": true,
          "notNull": true
        },
        "driver_id": {
          "name": "driver_id",
          "type": "text",
          "primaryKey": false,
          "notNull": true
        },
        "zone_id": {
          "name": "zone_id",
          "type": "text",
          "primaryKey": false,
          "notNull": true
        },
        "assigned_at": {
          "name": "assigned_at",
          "type": "timestamp with time zone",
          "primaryKey": false,
          "notNull": true,
          "default": "now()"
        }
      },
      "indexes": {},
      "foreignKeys": {
        "driver_zone_assignments_driver_id_driver_profiles_id_fk": {
          "name": "driver_zone_assignments_driver_id_driver_profiles_id_fk",
          "tableFrom": "driver_zone_assignments",
          "tableTo": "driver_profiles",
          "columnsFrom": [
            "driver_id"
          ],
          "columnsTo": [
            "id"
          ],
          "onDelete": "cascade",
          "onUpdate": "no action"
        },
        "driver_zone_assignments_zone_id_zones_id_fk": {
          "name": "driver_zone_assignments_zone_id_zones_id_fk",
          "tableFrom": "driver_zone_assignments",
          "tableTo": "zones",
          "columnsFrom": [
            "zone_id"
          ],
          "columnsTo": [
            "id"
          ],
          "onDelete": "cascade",
          "onUpdate": "no action"
        }
      },
      "compositePrimaryKeys": {},
      "uniqueConstraints": {
        "driver_zone_assignments_driver_id_zone_id_unique": {
          "name": "driver_zone_assignments_driver_id_zone_id_unique",
          "nullsNotDistinct": false,
          "columns": [
            "driver_id",
            "zone_id"
          ]
        }
      },
      "policies": {},
      "checkConstraints": {},
      "isRLSEnabled": false
    },
    "public.users": {
      "name": "users",
      "schema": "",
      "columns": {
        "id": {
          "name": "id",
          "type": "text",
          "primaryKey": true,
          "notNull": true
        },
        "email": {
          "name": "email",
          "type": "text",
          "primaryKey": false,
          "notNull": true
        },
        "password_hash": {
          "name": "password_hash",
          "type": "text",
          "primaryKey": false,
          "notNull": true
        },
        "first_name": {
          "name": "first_name",
          "type": "text",
          "primaryKey": false,
          "notNull": true
        },
        "last_name": {
          "name": "last_name",
          "type": "text",
          "primaryKey": false,
          "notNull": true
        },
        "phone": {
          "name": "phone",
          "type": "text",
          "primaryKey": false,
          "notNull": false
        },
        "role": {
          "name": "role",
          "type": "role",
          "typeSchema": "public",
          "primaryKey": false,
          "notNull": true,
          "default": "'customer'"
        },
        "is_active": {
          "name": "is_active",
          "type": "boolean",
          "primaryKey": false,
          "notNull": true,
          "default": true
        },
        "created_at": {
          "name": "created_at",
          "type": "timestamp with time zone",
          "primaryKey": false,
          "notNull": true,
          "default": "now()"
        },
        "updated_at": {
          "name": "updated_at",
          "type": "timestamp with time zone",
          "primaryKey": false,
          "notNull": true,
          "default": "now()"
        }
      },
      "indexes": {},
      "foreignKeys": {},
      "compositePrimaryKeys": {},
      "uniqueConstraints": {
        "users_email_unique": {
          "name": "users_email_unique",
          "nullsNotDistinct": false,
          "columns": [
            "email"
          ]
        }
      },
      "policies": {},
      "checkConstraints": {},
      "isRLSEnabled": false
    },
    "public.zones": {
      "name": "zones",
      "schema": "",
      "columns": {
        "id": {
          "name": "id",
          "type": "text",
          "primaryKey": true,
          "notNull": true
        },
        "city_id": {
          "name": "city_id",
          "type": "text",
          "primaryKey": false,
          "notNull": true
        },
        "name": {
          "name": "name",
          "type": "text",
          "primaryKey": false,
          "notNull": true
        },
        "description": {
          "name": "description",
          "type": "text",
          "primaryKey": false,
          "notNull": false
        },
        "is_active": {
          "name": "is_active",
          "type": "boolean",
          "primaryKey": false,
          "notNull": true,
          "default": true
        },
        "polygon": {
          "name": "polygon",
          "type": "json",
          "primaryKey": false,
          "notNull": true
        },
        "created_at": {
          "name": "created_at",
          "type": "timestamp with time zone",
          "primaryKey": false,
          "notNull": true,
          "default": "now()"
        },
        "updated_at": {
          "name": "updated_at",
          "type": "timestamp with time zone",
          "primaryKey": false,
          "notNull": true,
          "default": "now()"
        }
      },
      "indexes": {},
      "foreignKeys": {
        "zones_city_id_cities_id_fk": {
          "name": "zones_city_id_cities_id_fk",
          "tableFrom": "zones",
          "tableTo": "cities",
          "columnsFrom": [
            "city_id"
          ],
          "columnsTo": [
            "id"
          ],
          "onDelete": "no action",
          "onUpdate": "no action"
        }
      },
      "compositePrimaryKeys": {},
      "uniqueConstraints": {},
      "policies": {},
      "checkConstraints": {},
      "isRLSEnabled": false
    },
    "public.trip_events": {
      "name": "trip_events",
      "schema": "",
      "columns": {
        "id": {
          "name": "id",
          "type": "text",
          "primaryKey": true,
          "notNull": true
        },
        "trip_id": {
          "name": "trip_id",
          "type": "text",
          "primaryKey": false,
          "notNull": true
        },
        "status": {
          "name": "status",
          "type": "text",
          "primaryKey": false,
          "notNull": true
        },
        "actor_id": {
          "name": "actor_id",
          "type": "text",
          "primaryKey": false,
          "notNull": false
        },
        "actor_role": {
          "name": "actor_role",
          "type": "text",
          "primaryKey": false,
          "notNull": false
        },
        "metadata": {
          "name": "metadata",
          "type": "json",
          "primaryKey": false,
          "notNull": false
        },
        "created_at": {
          "name": "created_at",
          "type": "timestamp with time zone",
          "primaryKey": false,
          "notNull": true,
          "default": "now()"
        }
      },
      "indexes": {},
      "foreignKeys": {
        "trip_events_trip_id_trips_id_fk": {
          "name": "trip_events_trip_id_trips_id_fk",
          "tableFrom": "trip_events",
          "tableTo": "trips",
          "columnsFrom": [
            "trip_id"
          ],
          "columnsTo": [
            "id"
          ],
          "onDelete": "cascade",
          "onUpdate": "no action"
        }
      },
      "compositePrimaryKeys": {},
      "uniqueConstraints": {},
      "policies": {},
      "checkConstraints": {},
      "isRLSEnabled": false
    },
    "public.trips": {
      "name": "trips",
      "schema": "",
      "columns": {
        "id": {
          "name": "id",
          "type": "text",
          "primaryKey": true,
          "notNull": true
        },
        "customer_id": {
          "name": "customer_id",
          "type": "text",
          "primaryKey": false,
          "notNull": true
        },
        "driver_id": {
          "name": "driver_id",
          "type": "text",
          "primaryKey": false,
          "notNull": false
        },
        "city_id": {
          "name": "city_id",
          "type": "text",
          "primaryKey": false,
          "notNull": false
        },
        "pickup_lat": {
          "name": "pickup_lat",
          "type": "double precision",
          "primaryKey": false,
          "notNull": true
        },
        "pickup_lng": {
          "name": "pickup_lng",
          "type": "double precision",
          "primaryKey": false,
          "notNull": true
        },
        "pickup_address": {
          "name": "pickup_address",
          "type": "text",
          "primaryKey": false,
          "notNull": true
        },
        "dropoff_lat": {
          "name": "dropoff_lat",
          "type": "double precision",
          "primaryKey": false,
          "notNull": true
        },
        "dropoff_lng": {
          "name": "dropoff_lng",
          "type": "double precision",
          "primaryKey": false,
          "notNull": true
        },
        "dropoff_address": {
          "name": "dropoff_address",
          "type": "text",
          "primaryKey": false,
          "notNull": true
        },
        "status": {
          "name": "status",
          "type": "trip_status",
          "typeSchema": "public",
          "primaryKey": false,
          "notNull": true,
          "default": "'REQUESTED'"
        },
        "distance_km": {
          "name": "distance_km",
          "type": "double precision",
          "primaryKey": false,
          "notNull": false
        },
        "estimated_fare": {
          "name": "estimated_fare",
          "type": "numeric(10, 2)",
          "primaryKey": false,
          "notNull": false
        },
        "final_fare": {
          "name": "final_fare",
          "type": "numeric(10, 2)",
          "primaryKey": false,
          "notNull": false
        },
        "currency": {
          "name": "currency",
          "type": "text",
          "primaryKey": false,
          "notNull": true,
          "default": "'USD'"
        },
        "payment_method": {
          "name": "payment_method",
          "type": "payment_method",
          "typeSchema": "public",
          "primaryKey": false,
          "notNull": true,
          "default": "'cash'"
        },
        "cancellation_reason": {
          "name": "cancellation_reason",
          "type": "text",
          "primaryKey": false,
          "notNull": false
        },
        "notes": {
          "name": "notes",
          "type": "text",
          "primaryKey": false,
          "notNull": false
        },
        "requested_at": {
          "name": "requested_at",
          "type": "timestamp with time zone",
          "primaryKey": false,
          "notNull": true,
          "default": "now()"
        },
        "assigned_at": {
          "name": "assigned_at",
          "type": "timestamp with time zone",
          "primaryKey": false,
          "notNull": false
        },
        "started_at": {
          "name": "started_at",
          "type": "timestamp with time zone",
          "primaryKey": false,
          "notNull": false
        },
        "completed_at": {
          "name": "completed_at",
          "type": "timestamp with time zone",
          "primaryKey": false,
          "notNull": false
        },
        "created_at": {
          "name": "created_at",
          "type": "timestamp with time zone",
          "primaryKey": false,
          "notNull": true,
          "default": "now()"
        },
        "updated_at": {
          "name": "updated_at",
          "type": "timestamp with time zone",
          "primaryKey": false,
          "notNull": true,
          "default": "now()"
        }
      },
      "indexes": {},
      "foreignKeys": {
        "trips_customer_id_users_id_fk": {
          "name": "trips_customer_id_users_id_fk",
          "tableFrom": "trips",
          "tableTo": "users",
          "columnsFrom": [
            "customer_id"
          ],
          "columnsTo": [
            "id"
          ],
          "onDelete": "no action",
          "onUpdate": "no action"
        },
        "trips_driver_id_driver_profiles_id_fk": {
          "name": "trips_driver_id_driver_profiles_id_fk",
          "tableFrom": "trips",
          "tableTo": "driver_profiles",
          "columnsFrom": [
            "driver_id"
          ],
          "columnsTo": [
            "id"
          ],
          "onDelete": "no action",
          "onUpdate": "no action"
        },
        "trips_city_id_cities_id_fk": {
          "name": "trips_city_id_cities_id_fk",
          "tableFrom": "trips",
          "tableTo": "cities",
          "columnsFrom": [
            "city_id"
          ],
          "columnsTo": [
            "id"
          ],
          "onDelete": "no action",
          "onUpdate": "no action"
        }
      },
      "compositePrimaryKeys": {},
      "uniqueConstraints": {},
      "policies": {},
      "checkConstraints": {},
      "isRLSEnabled": false
    },
    "public.payments": {
      "name": "payments",
      "schema": "",
      "columns": {
        "id": {
          "name": "id",
          "type": "text",
          "primaryKey": true,
          "notNull": true
        },
        "trip_id": {
          "name": "trip_id",
          "type": "text",
          "primaryKey": false,
          "notNull": true
        },
        "amount": {
          "name": "amount",
          "type": "numeric(10, 2)",
          "primaryKey": false,
          "notNull": true
        },
        "currency": {
          "name": "currency",
          "type": "text",
          "primaryKey": false,
          "notNull": true,
          "default": "'USD'"
        },
        "method": {
          "name": "method",
          "type": "text",
          "primaryKey": false,
          "notNull": true,
          "default": "'cash'"
        },
        "status": {
          "name": "status",
          "type": "payment_status",
          "typeSchema": "public",
          "primaryKey": false,
          "notNull": true,
          "default": "'PENDING'"
        },
        "transaction_id": {
          "name": "transaction_id",
          "type": "text",
          "primaryKey": false,
          "notNull": false
        },
        "metadata": {
          "name": "metadata",
          "type": "json",
          "primaryKey": false,
          "notNull": false
        },
        "created_at": {
          "name": "created_at",
          "type": "timestamp with time zone",
          "primaryKey": false,
          "notNull": true,
          "default": "now()"
        },
        "updated_at": {
          "name": "updated_at",
          "type": "timestamp with time zone",
          "primaryKey": false,
          "notNull": true,
          "default": "now()"
        }
      },
      "indexes": {},
      "foreignKeys": {
        "payments_trip_id_trips_id_fk": {
          "name": "payments_trip_id_trips_id_fk",
          "tableFrom": "payments",
          "tableTo": "trips",
          "columnsFrom": [
            "trip_id"
          ],
          "columnsTo": [
            "id"
          ],
          "onDelete": "no action",
          "onUpdate": "no action"
        }
      },
      "compositePrimaryKeys": {},
      "uniqueConstraints": {},
      "policies": {},
      "checkConstraints": {},
      "isRLSEnabled": false
    }
  },
  "enums": {
    "public.driver_status": {
      "name": "driver_status",
      "schema": "public",
      "values": [
        "AVAILABLE",
        "RESERVED",
        "BUSY",
        "OFFLINE"
      ]
    },
    "public.role": {
      "name": "role",
      "schema": "public",
      "values": [
        "admin",
        "driver",
        "customer"
      ]
    },
    "public.payment_method": {
      "name": "payment_method",
      "schema": "public",
      "values": [
        "cash",
        "card",
        "online"
      ]
    },
    "public.trip_status": {
      "name": "trip_status",
      "schema": "public",
      "values": [
        "REQUESTED",
        "DRIVER_ASSIGNED",
        "DRIVER_ACCEPTED",
        "DRIVER_REJECTED",
        "DRIVER_EN_ROUTE",
        "DRIVER_ARRIVED",
        "TRIP_STARTED",
        "TRIP_COMPLETED",
        "TRIP_CANCELLED",
        "DRIVER_NO_RESPONSE",
        "TIMEOUT"
      ]
    },
    "public.payment_status": {
      "name": "payment_status",
      "schema": "public",
      "values": [
        "PENDING",
        "COMPLETED",
        "FAILED",
        "REFUNDED"
      ]
    }
  },
  "schemas": {},
  "sequences": {},
  "roles": {},
  "policies": {},
  "views": {},
  "_meta": {
    "columns": {},
    "schemas": {},
    "tables": {}
  }
}